aimrecords/__init__.py
aimrecords/__version__.py
aimrecords/artifact_storage/__init__.py
aimrecords/artifact_storage/consts.py
aimrecords/artifact_storage/storage.py
aimrecords/indexing/__init__.py
aimrecords/indexing/base.py
aimrecords/indexing/consts.py
aimrecords/indexing/index_key.py
aimrecords/indexing/reader.py
aimrecords/indexing/types.py
aimrecords/indexing/utils.py
aimrecords/indexing/writer.py
aimrecords/record_storage/__init__.py
aimrecords/record_storage/consts.py
aimrecords/record_storage/reader.py
aimrecords/record_storage/utils.py
aimrecords/record_storage/writer.py
tests/artifact_storage/__init__.py
tests/artifact_storage/basic_test.py
tests/artifact_storage/test_basic.py
tests/indexing/__init__.py
tests/indexing/test_basic.py
tests/indexing/test_finalize.py
tests/indexing/test_indexing.py
tests/record_storage/__init__.py
tests/record_storage/basic_test.py
tests/record_storage/compression_test.py
tests/record_storage/modes_test.py
tests/record_storage/modification_time_test.py
tests/record_storage/read_write_test.py
tests/record_storage/test_basic.py
tests/record_storage/test_compression.py
tests/record_storage/test_modes.py
tests/record_storage/test_modification_time.py
tests/record_storage/test_read_write.py
aimrecords-0.0.7.dist-info/LICENSE
aimrecords-0.0.7.dist-info/METADATA
aimrecords-0.0.7.dist-info/WHEEL
aimrecords-0.0.7.dist-info/top_level.txt
aimrecords-0.0.7.dist-info/RECORD
