Metadata-Version: 2.1
Name: aimrecords
Version: 0.0.7
Summary: A record-oriented data format which utilizes Protocol Buffers
Home-page: UNKNOWN
License: UNKNOWN
Platform: UNKNOWN
Classifier: License :: OSI Approved :: MIT License
Classifier: Programming Language :: Python
Classifier: Programming Language :: Python :: 3
Classifier: Programming Language :: Python :: 3.7
Classifier: Programming Language :: Python :: Implementation :: PyPy
Requires-Python: >=3.5.0
Requires-Dist: base58 (==2.0.1)
